README.txt
setup.py
collective/__init__.py
collective.recipe.rebar.egg-info/PKG-INFO
collective.recipe.rebar.egg-info/SOURCES.txt
collective.recipe.rebar.egg-info/dependency_links.txt
collective.recipe.rebar.egg-info/entry_points.txt
collective.recipe.rebar.egg-info/namespace_packages.txt
collective.recipe.rebar.egg-info/requires.txt
collective.recipe.rebar.egg-info/top_level.txt
collective.recipe.rebar.egg-info/zip-safe
collective/recipe/__init__.py
collective/recipe/rebar/__init__.py
collective/recipe/rebar/tests/__init__.py
collective/recipe/rebar/tests/test_docs.py