Metadata-Version: 1.0
Name: collective.recipe.rebar
Version: 1.0.1
Summary: Recipe for rebar based applications
Home-page: https://launchpad.net/collective.recipe.rebar
Author: Ali Sabil
Author-email: ali.sabil@gmail.com
License: ZPL
Keywords: rebar recipe buildout erlang
Platform: UNKNOWN
Classifier: Framework :: Buildout
Classifier: Intended Audience :: Developers
Classifier: Topic :: Software Development :: Build Tools
Classifier: License :: OSI Approved :: Zope Public License
